P_T_P1_package/__init__.py
P_T_P1_package/fifo.py
P_T_P1_package/lifo.py
P_T_P1_package/oq.py
P_T_P1_package/test_fifo.py
P_T_P1_package/test_lifo.py
P_T_P1_package/test_oq.py
P_T_P1_package-0.0.1.dist-info/LICENSE
P_T_P1_package-0.0.1.dist-info/METADATA
P_T_P1_package-0.0.1.dist-info/WHEEL
P_T_P1_package-0.0.1.dist-info/top_level.txt
P_T_P1_package-0.0.1.dist-info/RECORD
