Metadata-Version: 2.1
Name: P_T_P1_package
Version: 0.0.1
Summary: FIFO, LIFO, OQ
Author-email: JPMT <jeanpatricktorre@gmail.com>
Project-URL: Homepage, https://github.com/Rougon-Macquart/Patrick_Torre_Project_1_CMSC142
Classifier: Programming Language :: Python :: 3
Classifier: License :: Public Domain
Classifier: Operating System :: OS Independent
Requires-Python: >=3.8
License-File: LICENSE
